odoo/addons/l10n_br_fiscal_closing/README.rst
odoo/addons/l10n_br_fiscal_closing/__init__.py
odoo/addons/l10n_br_fiscal_closing/__manifest__.py
odoo/addons/l10n_br_fiscal_closing/i18n/l10n_br_fiscal_closing.pot
odoo/addons/l10n_br_fiscal_closing/i18n/pt_BR.po
odoo/addons/l10n_br_fiscal_closing/models/__init__.py
odoo/addons/l10n_br_fiscal_closing/models/closing.py
odoo/addons/l10n_br_fiscal_closing/models/document.py
odoo/addons/l10n_br_fiscal_closing/readme/CONFIGURE.md
odoo/addons/l10n_br_fiscal_closing/readme/CONTRIBUTORS.md
odoo/addons/l10n_br_fiscal_closing/readme/CREDITS.md
odoo/addons/l10n_br_fiscal_closing/readme/DESCRIPTION.md
odoo/addons/l10n_br_fiscal_closing/readme/HISTORY.md
odoo/addons/l10n_br_fiscal_closing/readme/INSTALL.md
odoo/addons/l10n_br_fiscal_closing/readme/ROADMAP.md
odoo/addons/l10n_br_fiscal_closing/readme/USAGE.md
odoo/addons/l10n_br_fiscal_closing/security/ir.model.access.csv
odoo/addons/l10n_br_fiscal_closing/static/description/icon.png
odoo/addons/l10n_br_fiscal_closing/static/description/index.html
odoo/addons/l10n_br_fiscal_closing/tests/__init__.py
odoo/addons/l10n_br_fiscal_closing/tests/test_fiscal_closing.py
odoo/addons/l10n_br_fiscal_closing/views/closing.xml
odoo_addon_l10n_br_fiscal_closing-16.0.2.6.0.dist-info/METADATA
odoo_addon_l10n_br_fiscal_closing-16.0.2.6.0.dist-info/WHEEL
odoo_addon_l10n_br_fiscal_closing-16.0.2.6.0.dist-info/top_level.txt
odoo_addon_l10n_br_fiscal_closing-16.0.2.6.0.dist-info/RECORD
